deocde_jzb/__init__.py
deocde_jzb/decode_jzb.py
deocde_jzb-0.0.3.dist-info/LICENSE
deocde_jzb-0.0.3.dist-info/METADATA
deocde_jzb-0.0.3.dist-info/WHEEL
deocde_jzb-0.0.3.dist-info/top_level.txt
deocde_jzb-0.0.3.dist-info/RECORD
